__init__.py
example.py
train_profiler.py
NFGen/__init__.py
NFGen/analysis.py
NFGen/code_generator.py
NFGen/data_preprocess.py
NFGen/fitter.py
NFGen/funcs.py
NFGen/main.py
NFGen/profiler.py
NFGen/CodeTemplet/__init__.py
NFGen/CodeTemplet/templet.py
NFGen/PerformanceModel/__init__.py
NFGen/PerformanceModel/time_ops.py
NFGen-0.0.2.dist-info/LICENSE
NFGen-0.0.2.dist-info/METADATA
NFGen-0.0.2.dist-info/WHEEL
NFGen-0.0.2.dist-info/top_level.txt
NFGen-0.0.2.dist-info/RECORD
