Metadata-Version: 2.1
Name: NFGen
Version: 0.0.2
Summary: NFGen: Automatic Non-Linear Function Evaluation Code Generator for General-purpose MPC Platforms
Author-email: Xiaoyu Fan <fanxy20@mails.tsinghua.edu.cn>
License: MIT License        
Project-URL: Homepage, https://github.com/Fannxy/NFGen
Project-URL: Bug Tracker, https://github.com/Fannxy/NFGen
Classifier: Programming Language :: Python :: 3
Classifier: License :: OSI Approved :: MIT License
Classifier: Operating System :: OS Independent
Requires-Python: >=3.8
License-File: LICENSE
